supermemory_pipecat/__init__.py
supermemory_pipecat/exceptions.py
supermemory_pipecat/service.py
supermemory_pipecat/utils.py
supermemory_pipecat-0.1.1.dist-info/METADATA
supermemory_pipecat-0.1.1.dist-info/WHEEL
supermemory_pipecat-0.1.1.dist-info/RECORD
