Metadata-Version: 2.4
Name: supermemory-pipecat
Version: 0.1.1
Summary: Supermemory integration for Pipecat - memory-enhanced conversational AI pipelines
Project-URL: Homepage, https://supermemory.ai
Project-URL: Documentation, https://docs.supermemory.ai
Project-URL: Repository, https://github.com/supermemoryai/supermemory
Author-email: Supermemory <support@supermemory.ai>
License-Expression: MIT
Keywords: conversational-ai,llm,memory,pipecat,supermemory,voice-ai
Classifier: Development Status :: 4 - Beta
Classifier: Intended Audience :: Developers
Classifier: License :: OSI Approved :: MIT License
Classifier: Programming Language :: Python :: 3
Classifier: Programming Language :: Python :: 3.10
Classifier: Programming Language :: Python :: 3.11
Classifier: Programming Language :: Python :: 3.12
Classifier: Topic :: Scientific/Engineering :: Artificial Intelligence
Requires-Python: >=3.10
Requires-Dist: loguru>=0.7.3
Requires-Dist: pipecat-ai>=0.0.98
Requires-Dist: pydantic>=2.10.0
Requires-Dist: supermemory>=3.16.0
Provides-Extra: dev
Requires-Dist: black>=24.8.0; extra == 'dev'
Requires-Dist: isort>=5.13.2; extra == 'dev'
Requires-Dist: mypy>=1.14.1; extra == 'dev'
Requires-Dist: pytest-asyncio>=0.24.0; extra == 'dev'
Requires-Dist: pytest>=8.3.5; extra == 'dev'
